morningstar_stmt
