Metadata-Version: 2.1
Name: morningstar-stmt
Version: 0.0.2
Summary: Morningstar Financials Statement Downloader
Home-page: https://github.com/xxiiaaon/morningstar-stmt
Author: xxiiaaon
Author-email: xxiiaaon@gmail.com
License: UNKNOWN
Platform: Any
Classifier: Programming Language :: Python :: 3
Classifier: License :: OSI Approved :: MIT License
Classifier: Operating System :: OS Independent
Requires-Python: >=3.6
